{"nodes": [{"id": "src_app_api_payments_route_ts", "label": "route.ts", "file_type": "code", "source_file": "src\\app\\api\\payments\\route.ts", "source_location": "L1"}, {"id": "route_post", "label": "POST()", "file_type": "code", "source_file": "src\\app\\api\\payments\\route.ts", "source_location": "L8"}, {"id": "route_get", "label": "GET()", "file_type": "code", "source_file": "src\\app\\api\\payments\\route.ts", "source_location": "L107"}], "edges": [{"source": "src_app_api_payments_route_ts", "target": "server", "relation": "imports_from", "confidence": "EXTRACTED", "source_file": "src\\app\\api\\payments\\route.ts", "source_location": "L1", "weight": 1.0}, {"source": "src_app_api_payments_route_ts", "target": "db", "relation": "imports_from", "confidence": "EXTRACTED", "source_file": "src\\app\\api\\payments\\route.ts", "source_location": "L2", "weight": 1.0}, {"source": "src_app_api_payments_route_ts", "target": "validators", "relation": "imports_from", "confidence": "EXTRACTED", "source_file": "src\\app\\api\\payments\\route.ts", "source_location": "L3", "weight": 1.0}, {"source": "src_app_api_payments_route_ts", "target": "logger", "relation": "imports_from", "confidence": "EXTRACTED", "source_file": "src\\app\\api\\payments\\route.ts", "source_location": "L4", "weight": 1.0}, {"source": "src_app_api_payments_route_ts", "target": "ratelimit", "relation": "imports_from", "confidence": "EXTRACTED", "source_file": "src\\app\\api\\payments\\route.ts", "source_location": "L5", "weight": 1.0}, {"source": "src_app_api_payments_route_ts", "target": "route_post", "relation": "contains", "confidence": "EXTRACTED", "source_file": "src\\app\\api\\payments\\route.ts", "source_location": "L8", "weight": 1.0}, {"source": "src_app_api_payments_route_ts", "target": "route_get", "relation": "contains", "confidence": "EXTRACTED", "source_file": "src\\app\\api\\payments\\route.ts", "source_location": "L107", "weight": 1.0}], "raw_calls": [{"caller_nid": "route_post", "callee": "checkRateLimit", "source_file": "src\\app\\api\\payments\\route.ts", "source_location": "L9"}, {"caller_nid": "route_post", "callee": "rateLimitKey", "source_file": "src\\app\\api\\payments\\route.ts", "source_location": "L9"}, {"caller_nid": "route_post", "callee": "json", "source_file": "src\\app\\api\\payments\\route.ts", "source_location": "L11"}, {"caller_nid": "route_post", "callee": "String", "source_file": "src\\app\\api\\payments\\route.ts", "source_location": "L13"}, {"caller_nid": "route_post", "callee": "ceil", "source_file": "src\\app\\api\\payments\\route.ts", "source_location": "L13"}, {"caller_nid": "route_post", "callee": "json", "source_file": "src\\app\\api\\payments\\route.ts", "source_location": "L17"}, {"caller_nid": "route_post", "callee": "safeParse", "source_file": "src\\app\\api\\payments\\route.ts", "source_location": "L18"}, {"caller_nid": "route_post", "callee": "json", "source_file": "src\\app\\api\\payments\\route.ts", "source_location": "L21"}, {"caller_nid": "route_post", "callee": "flatten", "source_file": "src\\app\\api\\payments\\route.ts", "source_location": "L21"}, {"caller_nid": "route_post", "callee": "$transaction", "source_file": "src\\app\\api\\payments\\route.ts", "source_location": "L27"}, {"caller_nid": "route_post", "callee": "json", "source_file": "src\\app\\api\\payments\\route.ts", "source_location": "L96"}, {"caller_nid": "route_post", "callee": "includes", "source_file": "src\\app\\api\\payments\\route.ts", "source_location": "L99"}, {"caller_nid": "route_post", "callee": "includes", "source_file": "src\\app\\api\\payments\\route.ts", "source_location": "L100"}, {"caller_nid": "route_post", "callee": "includes", "source_file": "src\\app\\api\\payments\\route.ts", "source_location": "L100"}, {"caller_nid": "route_post", "callee": "logError", "source_file": "src\\app\\api\\payments\\route.ts", "source_location": "L101"}, {"caller_nid": "route_post", "callee": "json", "source_file": "src\\app\\api\\payments\\route.ts", "source_location": "L102"}, {"caller_nid": "route_get", "callee": "checkRateLimit", "source_file": "src\\app\\api\\payments\\route.ts", "source_location": "L108"}, {"caller_nid": "route_get", "callee": "rateLimitKey", "source_file": "src\\app\\api\\payments\\route.ts", "source_location": "L108"}, {"caller_nid": "route_get", "callee": "json", "source_file": "src\\app\\api\\payments\\route.ts", "source_location": "L110"}, {"caller_nid": "route_get", "callee": "String", "source_file": "src\\app\\api\\payments\\route.ts", "source_location": "L112"}, {"caller_nid": "route_get", "callee": "ceil", "source_file": "src\\app\\api\\payments\\route.ts", "source_location": "L112"}, {"caller_nid": "route_get", "callee": "findMany", "source_file": "src\\app\\api\\payments\\route.ts", "source_location": "L117"}, {"caller_nid": "route_get", "callee": "parseInt", "source_file": "src\\app\\api\\payments\\route.ts", "source_location": "L118"}, {"caller_nid": "route_get", "callee": "json", "source_file": "src\\app\\api\\payments\\route.ts", "source_location": "L126"}]}